README
setup.py
asa_mptt/__init__.py
asa_mptt/events.py
asa_mptt/mixins.py
asa_mptt/mixins_base.py
asa_mptt.egg-info/PKG-INFO
asa_mptt.egg-info/SOURCES.txt
asa_mptt.egg-info/dependency_links.txt
asa_mptt.egg-info/requires.txt
asa_mptt.egg-info/top_level.txt