Metadata-Version: 1.0
Name: asa-mptt
Version: 1.1.5
Summary: Another SqlAlchemy MPTT
